x_client/__init__.py
x_client/aiohttp.py
x_client/http.py
xn_client-0.0.10.dist-info/METADATA
xn_client-0.0.10.dist-info/WHEEL
xn_client-0.0.10.dist-info/top_level.txt
xn_client-0.0.10.dist-info/RECORD
