Metadata-Version: 2.4
Name: xn-client
Version: 0.0.10
Author-email: Mike Artemiev <mixartemev@gmail.com>
License: MIT
Project-URL: Homepage, https://github.com/XyncNet/x-client
Project-URL: Repository, https://github.com/XyncNet/x-client
Requires-Python: >=3.11
Requires-Dist: aiohttp
Requires-Dist: brotli
Provides-Extra: dev
Requires-Dist: build; extra == "dev"
Requires-Dist: pytest-asyncio; extra == "dev"
Requires-Dist: pre-commit; extra == "dev"
Requires-Dist: python-dotenv; extra == "dev"
Requires-Dist: twine; extra == "dev"
